intersperse.py
intersperse-0.1.0a0.dist-info/licenses/LICENSE
intersperse-0.1.0a0.dist-info/METADATA
intersperse-0.1.0a0.dist-info/WHEEL
intersperse-0.1.0a0.dist-info/top_level.txt
intersperse-0.1.0a0.dist-info/RECORD
