Metadata-Version: 2.4
Name: intersperse
Version: 0.1.0a0
Summary: A simple Python generator that yields elements from an iterable, inserting a separator value between each element.
Author-email: Jifeng Wu <jifengwu2k@gmail.com>
License-Expression: MIT
Project-URL: Homepage, https://github.com/jifengwu2k/intersperse
Project-URL: Bug Tracker, https://github.com/jifengwu2k/intersperse/issues
Classifier: Programming Language :: Python :: 2
Classifier: Programming Language :: Python :: 3
Classifier: Operating System :: OS Independent
Requires-Python: >=2
License-File: LICENSE
Requires-Dist: typing; python_version < "3.5"
Dynamic: license-file
